src/__init__.py
src/main.py
cepapi-0.0.5.dist-info/METADATA
cepapi-0.0.5.dist-info/WHEEL
cepapi-0.0.5.dist-info/entry_points.txt
cepapi-0.0.5.dist-info/licenses/LICENSE
cepapi-0.0.5.dist-info/RECORD
