Metadata-Version: 2.3
Name: cepapi
Version: 0.0.5
Summary: A CLI for interacting with the Cloud Engineering Platform API
Project-URL: Homepage, https://www.redpointglobal.com/
Project-URL: Issues, https://support.redpointglobal.com
Author-email: Jim Musana <devops@redpointglobal.com>
License-File: LICENSE
Classifier: License :: OSI Approved :: MIT License
Classifier: Operating System :: OS Independent
Classifier: Programming Language :: Python :: 3
Requires-Python: >=3.8
Requires-Dist: click
Requires-Dist: httpx
Requires-Dist: rich
Requires-Dist: tqdm
